saracendb/__init__.py
saracendb-0.8.dist-info/METADATA
saracendb-0.8.dist-info/WHEEL
saracendb-0.8.dist-info/top_level.txt
saracendb-0.8.dist-info/RECORD
