Metadata-Version: 2.1
Name: saracendb
Version: 0.8
Author: Saracen Rhue
Author-email: 
Keywords: python,db
Classifier: Development Status :: 1 - Planning
Classifier: Intended Audience :: Developers
Classifier: Programming Language :: Python :: 3
Classifier: Operating System :: Unix
Classifier: Operating System :: MacOS :: MacOS X
Classifier: Operating System :: Microsoft :: Windows
Requires-Dist: pymongo
Requires-Dist: pyyaml
